nerna/__init__.py
nerna/nerna.py
nerna-0.2.1.dist-info/METADATA
nerna-0.2.1.dist-info/WHEEL
nerna-0.2.1.dist-info/licenses/LICENSE
nerna-0.2.1.dist-info/RECORD
