Metadata-Version: 2.4
Name: nerna
Version: 0.2.1
Summary: NERNA is a lightweight tool for annotating named entities directly within Python notebooks, ideal for quick and interactive NER tasks without the need for deployment or external servers.
License-File: LICENSE
Author: danttis
Author-email: juniordante01@gmail.com
Requires-Python: >=3.0
Classifier: Programming Language :: Python :: 3
Classifier: Programming Language :: Python :: 3.4
Classifier: Programming Language :: Python :: 3.5
Classifier: Programming Language :: Python :: 3.6
Classifier: Programming Language :: Python :: 3.7
Classifier: Programming Language :: Python :: 3.8
Classifier: Programming Language :: Python :: 3.9
Classifier: Programming Language :: Python :: 3.10
Classifier: Programming Language :: Python :: 3.11
Classifier: Programming Language :: Python :: 3.12
Classifier: Programming Language :: Python :: 3.13
Classifier: Programming Language :: Python :: 3.14
